vbiz/__init__.py
vbiz/ciddict.json
vbiz/command_line.py
vbiz/map.py
vbiz_fetcher/__init__.py
vbiz_fetcher/ciddict.json
vbiz_fetcher/command_line.py
vbiz_fetcher/map.py
vbiz_fetcher-0.0.28.dist-info/LICENSE
vbiz_fetcher-0.0.28.dist-info/METADATA
vbiz_fetcher-0.0.28.dist-info/WHEEL
vbiz_fetcher-0.0.28.dist-info/entry_points.txt
vbiz_fetcher-0.0.28.dist-info/top_level.txt
vbiz_fetcher-0.0.28.dist-info/RECORD
