Metadata-Version: 2.1
Name: vbiz-fetcher
Version: 0.0.28
Summary: The vBiz fetcher
Home-page: https://github.com/ltdangkhoa/vbiz_fetcher
Author: Kris Luu
Author-email: luuthaidangkhoa@gmail.com
License: UNKNOWN
Platform: UNKNOWN
Classifier: Programming Language :: Python :: 3
Classifier: License :: OSI Approved :: MIT License
Classifier: Operating System :: OS Independent
Requires-Dist: pdfminer.six
